wagtailsocialfeed/__init__.py
wagtailsocialfeed/blocks.py
wagtailsocialfeed/managers.py
wagtailsocialfeed/models.py
wagtailsocialfeed/urls.py
wagtailsocialfeed/views.py
wagtailsocialfeed/wagtail_hooks.py
wagtailsocialfeed/migrations/0001_initial.py
wagtailsocialfeed/migrations/0002_auto_20161005_1032.py
wagtailsocialfeed/migrations/0003_auto_20161006_1021.py
wagtailsocialfeed/migrations/__init__.py
wagtailsocialfeed/static/wagtailsocialfeed/css/admin/moderate-page.css
wagtailsocialfeed/static/wagtailsocialfeed/js/admin/moderate.js
wagtailsocialfeed/templates/wagtailsocialfeed/social_feed_block.html
wagtailsocialfeed/templates/wagtailsocialfeed/social_feed_page.html
wagtailsocialfeed/templates/wagtailsocialfeed/admin/header.html
wagtailsocialfeed/templates/wagtailsocialfeed/admin/moderate.html
wagtailsocialfeed/templates/wagtailsocialfeed/includes/feed_item.html
wagtailsocialfeed/utils/__init__.py
wagtailsocialfeed/utils/conf.py
wagtailsocialfeed/utils/feed/__init__.py
wagtailsocialfeed/utils/feed/facebook.py
wagtailsocialfeed/utils/feed/factory.py
wagtailsocialfeed/utils/feed/instagram.py
wagtailsocialfeed/utils/feed/twitter.py
wagtailsocialfeed-0.4.1.dist-info/DESCRIPTION.rst
wagtailsocialfeed-0.4.1.dist-info/METADATA
wagtailsocialfeed-0.4.1.dist-info/RECORD
wagtailsocialfeed-0.4.1.dist-info/WHEEL
wagtailsocialfeed-0.4.1.dist-info/metadata.json
wagtailsocialfeed-0.4.1.dist-info/top_level.txt
