Metadata-Version: 2.0
Name: wagtailsocialfeed
Version: 0.4.1
Summary: A Wagtail module that provides pages and content blocks to show social media feeds
Home-page: https://github.com/LUKKIEN/wagtailsocialfeed
Author: Tim Leguijt
Author-email: info@leguijtict.nl
License: BSD
Keywords: wagtailsocialfeed
Platform: UNKNOWN
Classifier: Development Status :: 2 - Pre-Alpha
Classifier: Intended Audience :: Developers
Classifier: License :: OSI Approved :: BSD License
Classifier: Natural Language :: English
Classifier: Programming Language :: Python :: 2
Classifier: Programming Language :: Python :: 2.7
Classifier: Programming Language :: Python :: 3
Classifier: Programming Language :: Python :: 3.3
Classifier: Programming Language :: Python :: 3.4
Classifier: Programming Language :: Python :: 3.5
Requires-Dist: enum34
Requires-Dist: facepy (>=1.0.8)
Requires-Dist: python-dateutil (>=2.5)
Requires-Dist: requests (>=2.0)
Requires-Dist: twython (>=3.0,<4.0)
Requires-Dist: wagtail (>=1.6)
Requires-Dist: wagtailfontawesome (>=1.0)
Provides-Extra: docs
Requires-Dist: sphinx; extra == 'docs'
Requires-Dist: sphinx-rtd-theme; extra == 'docs'
Provides-Extra: testing
Requires-Dist: PyYAML (==3.11); extra == 'testing'
Requires-Dist: beautifulsoup4 (>=4); extra == 'testing'
Requires-Dist: bumpversion (==0.5.3); extra == 'testing'
Requires-Dist: coverage (>=3.7.0); extra == 'testing'
Requires-Dist: cryptography (==1.4); extra == 'testing'
Requires-Dist: django-coverage-plugin (==1.3.1); extra == 'testing'
Requires-Dist: factory-boy (<2.9,>=2.8); extra == 'testing'
Requires-Dist: flake8 (>=2.2.0); extra == 'testing'
Requires-Dist: isort (>=4.2.0); extra == 'testing'
Requires-Dist: responses (>=0.5); extra == 'testing'
Requires-Dist: tox (>=2.3.1); extra == 'testing'
Requires-Dist: wheel (==0.29.0); extra == 'testing'
